revolve2/modular_robot/__init__.py
revolve2/modular_robot/_modular_robot.py
revolve2/modular_robot/_modular_robot_control_interface.py
revolve2/modular_robot/body/__init__.py
revolve2/modular_robot/body/_attachment_point.py
revolve2/modular_robot/body/_color.py
revolve2/modular_robot/body/_module.py
revolve2/modular_robot/body/_right_angles.py
revolve2/modular_robot/body/base/__init__.py
revolve2/modular_robot/body/base/_active_hinge.py
revolve2/modular_robot/body/base/_attachment_face.py
revolve2/modular_robot/body/base/_body.py
revolve2/modular_robot/body/base/_brick.py
revolve2/modular_robot/body/base/_core.py
revolve2/modular_robot/body/sensors/__init__.py
revolve2/modular_robot/body/sensors/_active_hinge_sensor.py
revolve2/modular_robot/body/sensors/_camera_sensor.py
revolve2/modular_robot/body/sensors/_imu_sensor.py
revolve2/modular_robot/body/sensors/_sensor.py
revolve2/modular_robot/body/v1/__init__.py
revolve2/modular_robot/body/v1/_active_hinge_v1.py
revolve2/modular_robot/body/v1/_body_v1.py
revolve2/modular_robot/body/v1/_brick_v1.py
revolve2/modular_robot/body/v1/_core_v1.py
revolve2/modular_robot/body/v2/__init__.py
revolve2/modular_robot/body/v2/_active_hinge_v2.py
revolve2/modular_robot/body/v2/_attachment_face_core_v2.py
revolve2/modular_robot/body/v2/_body_v2.py
revolve2/modular_robot/body/v2/_brick_v2.py
revolve2/modular_robot/body/v2/_core_v2.py
revolve2/modular_robot/brain/__init__.py
revolve2/modular_robot/brain/_brain.py
revolve2/modular_robot/brain/_brain_instance.py
revolve2/modular_robot/brain/cpg/__init__.py
revolve2/modular_robot/brain/cpg/_brain_cpg_instance.py
revolve2/modular_robot/brain/cpg/_brain_cpg_network_neighbor.py
revolve2/modular_robot/brain/cpg/_brain_cpg_network_neighbor_random.py
revolve2/modular_robot/brain/cpg/_brain_cpg_network_static.py
revolve2/modular_robot/brain/cpg/_cpg_network_structure.py
revolve2/modular_robot/brain/cpg/_make_cpg_network_structure_neighbor.py
revolve2/modular_robot/brain/dummy/__init__.py
revolve2_modular_robot-1.2.4.dist-info/METADATA
revolve2_modular_robot-1.2.4.dist-info/WHEEL
revolve2_modular_robot-1.2.4.dist-info/RECORD
